{
  "annotations": {
    "list": []
  },
  "editable": true,
  "fiscalYearStartMonth": 0,
  "graphTooltip": 0,
  "id": null,
  "links": [],
  "liveNow": false,
  "panels": [
    {
      "datasource": {
        "type": "prometheus",
        "name": "Prometheus"
      },
      "fieldConfig": {
        "defaults": {
          "mappings": [
            {
              "options": {
                "0": {
                  "text": "OFFLINE",
                  "color": "red"
                },
                "1": {
                  "text": "ONLINE",
                  "color": "green"
                }
              },
              "type": "value"
            }
          ],
          "thresholds": {
            "steps": [
              {"color": "red", "value": 0},
              {"color": "green", "value": 1}
            ]
          }
        }
      },
      "gridPos": {"h": 6, "w": 4, "x": 0, "y": 0},
      "id": 1,
      "options": {
        "reduceOptions": {
          "values": false,
          "calcs": ["lastNotNull"],
          "fields": ""
        }
      },
      "targets": [
        {
          "datasource": {
            "type": "prometheus",
            "name": "Prometheus"
          },
          "expr": "up{job=\"vendas-api\"}",
          "legendFormat": "Status",
          "refId": "A"
        }
      ],
      "title": "Status da Aplicação",
      "type": "stat"
    },
    {
      "datasource": {
        "type": "prometheus",
        "name": "Prometheus"
      },
      "fieldConfig": {
        "defaults": {
          "color": {
            "mode": "thresholds"
          },
          "thresholds": {
            "steps": [
              {"color": "green", "value": 0},
              {"color": "yellow", "value": 50},
              {"color": "orange", "value": 100}
            ]
          },
          "unit": "short"
        }
      },
      "gridPos": {"h": 6, "w": 4, "x": 4, "y": 0},
      "id": 3,
      "options": {
        "reduceOptions": {
          "values": false,
          "calcs": ["lastNotNull"],
          "fields": ""
        }
      },
      "targets": [
        {
          "datasource": {
            "type": "prometheus",
            "name": "Prometheus"
          },
          "expr": "vendas_eventos_total{job=\"vendas-api\", evento=\"criada\"}",
          "legendFormat": "Vendas Criadas",
          "refId": "A"
        }
      ],
      "title": "Vendas Criadas",
      "type": "stat"
    },
    {
      "datasource": {
        "type": "prometheus",
        "name": "Prometheus"
      },
      "fieldConfig": {
        "defaults": {
          "color": {
            "mode": "thresholds"
          },
          "thresholds": {
            "steps": [
              {"color": "green", "value": 0},
              {"color": "yellow", "value": 10},
              {"color": "red", "value": 25}
            ]
          },
          "unit": "short"
        }
      },
      "gridPos": {"h": 6, "w": 4, "x": 8, "y": 0},
      "id": 4,
      "options": {
        "reduceOptions": {
          "values": false,
          "calcs": ["lastNotNull"],
          "fields": ""
        }
      },
      "targets": [
        {
          "datasource": {
            "type": "prometheus",
            "name": "Prometheus"
          },
          "expr": "vendas_eventos_total{job=\"vendas-api\", evento=\"cancelada\"}",
          "legendFormat": "Vendas Canceladas",
          "refId": "A"
        }
      ],
      "title": "Vendas Canceladas",
      "type": "stat"
    },
    {
      "datasource": {
        "type": "prometheus",
        "name": "Prometheus"
      },
      "fieldConfig": {
        "defaults": {
          "custom": {
            "drawStyle": "line",
            "lineInterpolation": "linear",
            "fillOpacity": 10
          }
        }
      },
      "gridPos": {"h": 6, "w": 8, "x": 12, "y": 0},
      "id": 2,
      "targets": [
        {
          "datasource": {
            "type": "prometheus",
            "name": "Prometheus"
          },
          "expr": "rate(http_server_requests_seconds_count{job=\"vendas-api\"}[1m])",
          "legendFormat": "{{method}} {{uri}}",
          "refId": "A"
        }
      ],
      "title": "Requests por Segundo",
      "type": "timeseries"
    }
  ],
  "refresh": "5s",
  "schemaVersion": 38,
  "style": "dark",
  "tags": ["vendas", "spring-boot", "api"],
  "templating": {
    "list": []
  },
  "time": {
    "from": "now-1h",
    "to": "now"
  },
  "timepicker": {},
  "timezone": "",
  "title": "Vendas API - Monitoramento",
  "uid": "vendas-api-001",
  "version": 1,
  "weekStart": ""
}